cashit_sdk/__init__.py
cashit_sdk/client.py
cashit_sdk/exceptions.py
cashit_sdk/models.py
cashit_sdk-1.0.0.dist-info/licenses/LICENSE
cashit_sdk-1.0.0.dist-info/METADATA
cashit_sdk-1.0.0.dist-info/WHEEL
cashit_sdk-1.0.0.dist-info/top_level.txt
cashit_sdk-1.0.0.dist-info/RECORD
