Metadata-Version: 2.4
Name: cashit_sdk
Version: 1.0.0
Summary: Python SDK for CashIt cheque APIs
Author: Tekku
License-File: LICENSE
Requires-Dist: requests
Requires-Dist: cloudinary
Dynamic: author
Dynamic: license-file
Dynamic: requires-dist
Dynamic: summary
